packse/__init__.py
packse/__main__.py
packse/build.py
packse/cli.py
packse/error.py
packse/fetch.py
packse/index.py
packse/inspect.py
packse/list.py
packse/publish.py
packse/scenario.py
packse/serve.py
packse/template.py
packse/view.py
packse/templates/__init__.py
packse/templates/index/index.html
packse/templates/index/simple-html/index.html
packse/templates/index/simple-html/[[ scenarios ]][[ packages ]]{{ name}}/index.html
packse/templates/package/template.toml
packse/templates/package/{{ package-name }}-{{ version }}/.gitignore
packse/templates/package/{{ package-name }}-{{ version }}/pyproject.toml
packse/templates/package/{{ package-name }}-{{ version }}/src/{{ module-name }}/__init__.py
packse-0.3.53.dist-info/METADATA
packse-0.3.53.dist-info/WHEEL
packse-0.3.53.dist-info/entry_points.txt
packse-0.3.53.dist-info/licenses/LICENSE-APACHE
packse-0.3.53.dist-info/licenses/LICENSE-MIT
packse-0.3.53.dist-info/RECORD
