Metadata-Version: 2.4
Name: packse
Version: 0.3.53
Author-email: "Astral Software Inc." <hey@astral.sh>
License-File: LICENSE-APACHE
License-File: LICENSE-MIT
Keywords: packaging,packse,requirements,testing,uv
Classifier: Development Status :: 4 - Beta
Classifier: Environment :: Console
Classifier: Intended Audience :: Developers
Classifier: License :: OSI Approved :: Apache Software License
Classifier: License :: OSI Approved :: MIT License
Classifier: Operating System :: OS Independent
Classifier: Programming Language :: Python
Classifier: Programming Language :: Python :: 3 :: Only
Classifier: Programming Language :: Python :: 3.12
Classifier: Topic :: Software Development :: Libraries
Classifier: Topic :: Software Development :: Quality Assurance
Classifier: Topic :: Software Development :: Testing
Requires-Python: >=3.12
Requires-Dist: chevron-blue>=0.2.1
Requires-Dist: hatchling>=1.20.0
Requires-Dist: msgspec>=0.18.4
Requires-Dist: pyyaml>=6.0.1
Requires-Dist: uv>=0.8
Provides-Extra: index
Requires-Dist: fastapi>=0.116.1; extra == 'index'
Requires-Dist: starlette>=0.47.3; extra == 'index'
Requires-Dist: uvicorn>=0.35.0; extra == 'index'
Provides-Extra: serve
Requires-Dist: fastapi>=0.116.1; extra == 'serve'
Requires-Dist: starlette>=0.47.3; extra == 'serve'
Requires-Dist: uvicorn>=0.35.0; extra == 'serve'
Requires-Dist: watchfiles>=0.21.0; extra == 'serve'
